ftui/__init__.py
ftui/freqtext.css
ftui/ftui.py
ftui/ftui_client.py
ftui/ftui_helpers.py
ftui/md/help.md
ftui/screens/dashboard_screen.py
ftui/screens/help_screen.py
ftui/screens/main_bot_screen.py
ftui/screens/modal_screens.py
ftui/screens/settings_screen.py
ftui/widgets/label_item.py
ftui/widgets/linkable_markdown_viewer.py
ftui/widgets/timed_screen.py
ftui-0.1.12.dist-info/METADATA
ftui-0.1.12.dist-info/WHEEL
ftui-0.1.12.dist-info/entry_points.txt
ftui-0.1.12.dist-info/licenses/LICENSE
ftui-0.1.12.dist-info/RECORD
