Metadata-Version: 2.4
Name: ftui
Version: 0.1.12
Summary: Freqtrade TUI
Project-URL: Homepage, https://github.com/freqtrade/ftui
Project-URL: Documentation, https://freqtrade.io
Project-URL: Bug Tracker, https://github.com/freqtrade/ftui/issues
Author: froggleston
Author-email: Freqtrade Team <freqtrade@protonmail.com>
License: MIT
License-File: LICENSE
Classifier: Environment :: Console
Classifier: Intended Audience :: Science/Research
Classifier: License :: OSI Approved :: MIT License
Classifier: Operating System :: MacOS
Classifier: Operating System :: Microsoft :: Windows
Classifier: Operating System :: Unix
Classifier: Programming Language :: Python :: 3.9
Classifier: Programming Language :: Python :: 3.10
Classifier: Programming Language :: Python :: 3.11
Classifier: Programming Language :: Python :: 3.12
Classifier: Topic :: Office/Business :: Financial :: Investment
Requires-Python: >=3.9
Requires-Dist: freqtrade-client
Requires-Dist: numpy
Requires-Dist: pandas
Requires-Dist: plotext==5.2.8
Requires-Dist: python-rapidjson
Requires-Dist: pyyaml
Requires-Dist: requests
Requires-Dist: textual-plotext==0.2.1
Requires-Dist: textual==0.85.0
